conversion_therapy/__init__.py
conversion_therapy/cli.py
conversion_therapy/conversion_therapy.py
conversion_therapy-0.1.0.dist-info/DESCRIPTION.rst
conversion_therapy-0.1.0.dist-info/METADATA
conversion_therapy-0.1.0.dist-info/RECORD
conversion_therapy-0.1.0.dist-info/WHEEL
conversion_therapy-0.1.0.dist-info/entry_points.txt
conversion_therapy-0.1.0.dist-info/metadata.json
conversion_therapy-0.1.0.dist-info/top_level.txt
