Metadata-Version: 2.0
Name: conversion-therapy
Version: 0.1.0
Summary: Universal Data Conversion Library and CLI
Home-page: https://github.com/likeshumidity/conversion_therapy
Author: Jacob S J Joseph
Author-email: jacobsjjoseph@gmail.com
License: MIT license
Keywords: conversion_therapy file conversion data converter universal
Platform: UNKNOWN
Classifier: Development Status :: 1 - Planning
Classifier: Environment :: Console
Classifier: Intended Audience :: Developers
Classifier: Intended Audience :: Science/Research
Classifier: Intended Audience :: Information Technology
Classifier: License :: OSI Approved :: MIT License
Classifier: Natural Language :: English
Classifier: Programming Language :: Python :: 3
Classifier: Programming Language :: Python :: 3.4
Classifier: Programming Language :: Python :: 3.5
Classifier: Programming Language :: Python :: 3.6
Classifier: Topic :: Text Processing
Requires-Python: >=3
Requires-Dist: Click (>=6.0)
